infolib/__init__.py
infolib/infolib.py
infolib-0.2.21.dist-info/LICENSE
infolib-0.2.21.dist-info/METADATA
infolib-0.2.21.dist-info/WHEEL
infolib-0.2.21.dist-info/entry_points.txt
infolib-0.2.21.dist-info/top_level.txt
infolib-0.2.21.dist-info/RECORD
